django_opentracing_logger/__init__.py
django_opentracing_logger/opentracing/__init__.py
django_opentracing_logger/opentracing/constant.py
django_opentracing_logger/opentracing/context.py
django_opentracing_logger/opentracing/endpoint.py
django_opentracing_logger/opentracing/logging.py
django_opentracing_logger/opentracing/middleware.py
django_opentracing_logger/opentracing/reporter.py
django_opentracing_logger/opentracing/sampler.py
django_opentracing_logger/opentracing/span.py
django_opentracing_logger/opentracing/tags.py
django_opentracing_logger/opentracing/tracer.py
django_opentracing_logger/opentracing/utils.py
django_opentracing_logger-0.0.2.dist-info/LICENSE
django_opentracing_logger-0.0.2.dist-info/METADATA
django_opentracing_logger-0.0.2.dist-info/WHEEL
django_opentracing_logger-0.0.2.dist-info/top_level.txt
django_opentracing_logger-0.0.2.dist-info/RECORD
