Metadata-Version: 2.1
Name: django-opentracing-logger
Version: 0.0.2
Summary: django opentracing SDK based on logger which focus on ease to use
Home-page: https://github.com/FingerLiu/django-opentracing-logger
Author: liupeng
Author-email: liupeng@luojilab.com
License: BSD License
Platform: UNKNOWN
Classifier: Environment :: Web Environment
Classifier: Framework :: Django
Classifier: Intended Audience :: Developers
Classifier: License :: OSI Approved :: BSD License
Classifier: Operating System :: OS Independent
Classifier: Programming Language :: Python
Classifier: Programming Language :: Python :: 3.6
Classifier: Topic :: Internet :: WWW/HTTP
Classifier: Topic :: System :: Distributed Computing
Classifier: Topic :: Software Development :: Libraries :: Python Modules
Requires-Dist: Django (>=1.11)
